{
    "player_0": {
        "@Commander": 10,
        "@Constructor": 15,
        "@Droid": 101,
        "A0ComDroidControl": 1,
        "A0CommandCentre": 1,
        "A0CommandCentreCO": 5,
        "A0CommandCentreNE": 5,
        "A0CommandCentreNP": 5,
        "A0CyborgFactory": 5,
        "A0LightFactory": 5,
        "A0PowerGenerator": 5,
        "A0ResearchFacility": 5,
        "A0ResourceExtractor": 200,
        "A0VTolFactory1": 5
    },
    "player_1": {
        "@Commander": 32767,
        "@Constructor": 32767,
        "@Droid": 32767,
        "A0ComDroidControl": 5,
        "A0CommandCentre": 5,
        "A0CommandCentreCO": 5,
        "A0CommandCentreNE": 5,
        "A0CommandCentreNP": 5,
        "A0CyborgFactory": 5,
        "A0LightFactory": 5,
        "A0PowerGenerator": 5,
        "A0ResearchFacility": 5,
        "A0ResourceExtractor": 200,
        "A0VTolFactory1": 5
    },
    "player_2": {
        "@Commander": 32767,
        "@Constructor": 32767,
        "@Droid": 32767,
        "A0ComDroidControl": 5,
        "A0CommandCentre": 5,
        "A0CommandCentreCO": 5,
        "A0CommandCentreNE": 5,
        "A0CommandCentreNP": 5,
        "A0CyborgFactory": 5,
        "A0LightFactory": 5,
        "A0PowerGenerator": 5,
        "A0ResearchFacility": 5,
        "A0ResourceExtractor": 200,
        "A0VTolFactory1": 5
    },
    "player_3": {
        "@Commander": 32767,
        "@Constructor": 32767,
        "@Droid": 32767,
        "A0ComDroidControl": 5,
        "A0CommandCentre": 5,
        "A0CommandCentreCO": 5,
        "A0CommandCentreNE": 5,
        "A0CommandCentreNP": 5,
        "A0CyborgFactory": 5,
        "A0LightFactory": 5,
        "A0PowerGenerator": 5,
        "A0ResearchFacility": 5,
        "A0ResourceExtractor": 200,
        "A0VTolFactory1": 5
    },
    "player_4": {
        "@Commander": 32767,
        "@Constructor": 32767,
        "@Droid": 32767,
        "A0ComDroidControl": 5,
        "A0CommandCentre": 5,
        "A0CommandCentreCO": 5,
        "A0CommandCentreNE": 5,
        "A0CommandCentreNP": 5,
        "A0CyborgFactory": 5,
        "A0LightFactory": 5,
        "A0PowerGenerator": 5,
        "A0ResearchFacility": 5,
        "A0ResourceExtractor": 200,
        "A0VTolFactory1": 5
    },
    "player_5": {
        "@Commander": 32767,
        "@Constructor": 32767,
        "@Droid": 32767,
        "A0ComDroidControl": 5,
        "A0CommandCentre": 5,
        "A0CommandCentreCO": 5,
        "A0CommandCentreNE": 5,
        "A0CommandCentreNP": 5,
        "A0CyborgFactory": 5,
        "A0LightFactory": 5,
        "A0PowerGenerator": 5,
        "A0ResearchFacility": 5,
        "A0ResourceExtractor": 200,
        "A0VTolFactory1": 5
    },
    "player_6": {
        "@Commander": 32767,
        "@Constructor": 32767,
        "@Droid": 32767,
        "A0ComDroidControl": 5,
        "A0CommandCentre": 5,
        "A0CommandCentreCO": 5,
        "A0CommandCentreNE": 5,
        "A0CommandCentreNP": 5,
        "A0CyborgFactory": 5,
        "A0LightFactory": 5,
        "A0PowerGenerator": 5,
        "A0ResearchFacility": 5,
        "A0ResourceExtractor": 200,
        "A0VTolFactory1": 5
    },
    "player_7": {
        "@Commander": 32767,
        "@Constructor": 32767,
        "@Droid": 32767,
        "A0ComDroidControl": 5,
        "A0CommandCentre": 5,
        "A0CommandCentreCO": 5,
        "A0CommandCentreNE": 5,
        "A0CommandCentreNP": 5,
        "A0CyborgFactory": 5,
        "A0LightFactory": 5,
        "A0PowerGenerator": 5,
        "A0ResearchFacility": 5,
        "A0ResourceExtractor": 200,
        "A0VTolFactory1": 5
    },
    "player_8": {
        "@Commander": 32767,
        "@Constructor": 32767,
        "@Droid": 32767,
        "A0ComDroidControl": 5,
        "A0CommandCentre": 5,
        "A0CommandCentreCO": 5,
        "A0CommandCentreNE": 5,
        "A0CommandCentreNP": 5,
        "A0CyborgFactory": 5,
        "A0LightFactory": 5,
        "A0PowerGenerator": 5,
        "A0ResearchFacility": 5,
        "A0ResourceExtractor": 200,
        "A0VTolFactory1": 5
    },
    "player_9": {
        "@Commander": 32767,
        "@Constructor": 32767,
        "@Droid": 32767,
        "A0ComDroidControl": 5,
        "A0CommandCentre": 5,
        "A0CommandCentreCO": 5,
        "A0CommandCentreNE": 5,
        "A0CommandCentreNP": 5,
        "A0CyborgFactory": 5,
        "A0LightFactory": 5,
        "A0PowerGenerator": 5,
        "A0ResearchFacility": 5,
        "A0ResourceExtractor": 200,
        "A0VTolFactory1": 5
    }
}
